arope_universal_life/__init__.py
arope_universal_life/abstracted_packages.py
arope_universal_life/aggregation_results.py
arope_universal_life/arope_full_workflow.py
arope_universal_life/arope_universal_life_workflow.py
arope_universal_life/universal_life_module.py
arope_universal_life/modules/__init__.py
arope_universal_life/modules/validator_dfs.py
arope_universal_life/modules/model_point_generator/__init__.py
arope_universal_life/modules/model_point_generator/model_point_generator.py
arope_universal_life/modules/model_point_generator/policies_refinement.py
arope_universal_life/modules/universal_life/__init__.py
arope_universal_life/modules/universal_life/merge_all_df.py
arope_universal_life/modules/universal_life/required_data_calculation.py
arope_universal_life/modules/universal_life/run.py
arope_universal_life/modules/universal_life/tools.py
arope_universal_life/modules/universal_life/sub_modules/_1_duration.py
arope_universal_life/modules/universal_life/sub_modules/_2_reserve.py
arope_universal_life/modules/universal_life/sub_modules/_2_reserve_old.py
arope_universal_life/modules/universal_life/sub_modules/_3_proba.py
arope_universal_life/modules/universal_life/sub_modules/_4_prospective.py
arope_universal_life/modules/universal_life/sub_modules/__init__.py
inputs/__init__.py
inputs/product.csv
inputs/ri_rates.csv
inputs/tech_assumptions.csv
inputs/wop_rates.csv
arope_universal_life-0.1.5.dist-info/METADATA
arope_universal_life-0.1.5.dist-info/WHEEL
arope_universal_life-0.1.5.dist-info/top_level.txt
arope_universal_life-0.1.5.dist-info/RECORD
